README.md
setup.py
cc/__init__.py
command_controller.egg-info/PKG-INFO
command_controller.egg-info/SOURCES.txt
command_controller.egg-info/dependency_links.txt
command_controller.egg-info/not-zip-safe
command_controller.egg-info/top_level.txt